{"file":"btn.png","frames":{
"59":{"x":212,"y":222,"w":209,"h":215,"offX":0,"offY":0,"sourceW":209,"sourceH":215},
"60":{"x":837,"y":1,"w":207,"h":219,"offX":0,"offY":0,"sourceW":207,"sourceH":219},
"61":{"x":628,"y":1,"w":207,"h":219,"offX":0,"offY":0,"sourceW":207,"sourceH":219},
"62":{"x":1468,"y":218,"w":209,"h":215,"offX":0,"offY":0,"sourceW":209,"sourceH":215},
"63":{"x":1257,"y":218,"w":209,"h":215,"offX":0,"offY":0,"sourceW":209,"sourceH":215},
"64":{"x":1046,"y":218,"w":209,"h":215,"offX":0,"offY":0,"sourceW":209,"sourceH":215},
"65":{"x":1679,"y":1,"w":209,"h":215,"offX":0,"offY":0,"sourceW":209,"sourceH":215},
"66":{"x":1468,"y":1,"w":209,"h":215,"offX":0,"offY":0,"sourceW":209,"sourceH":215},
"67":{"x":419,"y":1,"w":207,"h":219,"offX":0,"offY":0,"sourceW":207,"sourceH":219},
"68":{"x":1046,"y":1,"w":209,"h":215,"offX":0,"offY":0,"sourceW":209,"sourceH":215},
"69":{"x":1,"y":222,"w":209,"h":215,"offX":0,"offY":0,"sourceW":209,"sourceH":215},
"70":{"x":210,"y":1,"w":207,"h":219,"offX":0,"offY":0,"sourceW":207,"sourceH":219},
"71":{"x":1257,"y":1,"w":209,"h":215,"offX":0,"offY":0,"sourceW":209,"sourceH":215},
"72":{"x":1,"y":439,"w":364,"h":116,"offX":0,"offY":0,"sourceW":364,"sourceH":116},
"73":{"x":1363,"y":435,"w":364,"h":116,"offX":0,"offY":0,"sourceW":364,"sourceH":116},
"74":{"x":997,"y":435,"w":364,"h":116,"offX":0,"offY":0,"sourceW":364,"sourceH":116},
"75":{"x":631,"y":340,"w":364,"h":116,"offX":0,"offY":0,"sourceW":364,"sourceH":116},
"76":{"x":631,"y":222,"w":364,"h":116,"offX":0,"offY":0,"sourceW":364,"sourceH":116},
"77":{"x":1465,"y":553,"w":364,"h":116,"offX":0,"offY":0,"sourceW":364,"sourceH":116},
"78":{"x":1099,"y":553,"w":364,"h":116,"offX":0,"offY":0,"sourceW":364,"sourceH":116},
"79":{"x":733,"y":553,"w":364,"h":116,"offX":0,"offY":0,"sourceW":364,"sourceH":116},
"80":{"x":367,"y":458,"w":364,"h":116,"offX":0,"offY":0,"sourceW":364,"sourceH":116},
"0":{"x":1973,"y":771,"w":62,"h":110,"offX":0,"offY":0,"sourceW":62,"sourceH":110},
"1":{"x":1729,"y":435,"w":62,"h":110,"offX":0,"offY":0,"sourceW":62,"sourceH":110},
"2":{"x":669,"y":985,"w":62,"h":110,"offX":0,"offY":0,"sourceW":62,"sourceH":110},
"3":{"x":605,"y":985,"w":62,"h":110,"offX":0,"offY":0,"sourceW":62,"sourceH":110},
"4":{"x":541,"y":896,"w":62,"h":110,"offX":0,"offY":0,"sourceW":62,"sourceH":110},
"5":{"x":1605,"y":839,"w":62,"h":110,"offX":0,"offY":0,"sourceW":62,"sourceH":110},
"6":{"x":817,"y":458,"w":82,"h":82,"offX":0,"offY":0,"sourceW":82,"sourceH":82},
"7":{"x":733,"y":458,"w":82,"h":82,"offX":0,"offY":0,"sourceW":82,"sourceH":82},
"8":{"x":901,"y":458,"w":82,"h":82,"offX":0,"offY":0,"sourceW":82,"sourceH":82},
"9":{"x":885,"y":839,"w":118,"h":118,"offX":0,"offY":0,"sourceW":118,"sourceH":118},
"10":{"x":1890,"y":307,"w":118,"h":118,"offX":0,"offY":0,"sourceW":118,"sourceH":118},
"11":{"x":1,"y":878,"w":118,"h":118,"offX":0,"offY":0,"sourceW":118,"sourceH":118},
"12":{"x":1485,"y":839,"w":118,"h":118,"offX":0,"offY":0,"sourceW":118,"sourceH":118},
"13":{"x":1365,"y":839,"w":118,"h":118,"offX":0,"offY":0,"sourceW":118,"sourceH":118},
"14":{"x":1245,"y":839,"w":118,"h":118,"offX":0,"offY":0,"sourceW":118,"sourceH":118},
"15":{"x":1125,"y":839,"w":118,"h":118,"offX":0,"offY":0,"sourceW":118,"sourceH":118},
"16":{"x":1005,"y":839,"w":118,"h":118,"offX":0,"offY":0,"sourceW":118,"sourceH":118},
"17":{"x":1083,"y":959,"w":112,"h":112,"offX":0,"offY":0,"sourceW":112,"sourceH":112},
"18":{"x":969,"y":959,"w":112,"h":112,"offX":0,"offY":0,"sourceW":112,"sourceH":112},
"19":{"x":755,"y":982,"w":112,"h":112,"offX":0,"offY":0,"sourceW":112,"sourceH":112},
"20":{"x":1653,"y":963,"w":112,"h":112,"offX":0,"offY":0,"sourceW":112,"sourceH":112},
"21":{"x":1539,"y":959,"w":112,"h":112,"offX":0,"offY":0,"sourceW":112,"sourceH":112},
"22":{"x":1425,"y":959,"w":112,"h":112,"offX":0,"offY":0,"sourceW":112,"sourceH":112},
"23":{"x":1311,"y":959,"w":112,"h":112,"offX":0,"offY":0,"sourceW":112,"sourceH":112},
"24":{"x":1197,"y":959,"w":112,"h":112,"offX":0,"offY":0,"sourceW":112,"sourceH":112},
"25":{"x":755,"y":839,"w":128,"h":141,"offX":0,"offY":0,"sourceW":128,"sourceH":141},
"26":{"x":121,"y":878,"w":82,"h":168,"offX":0,"offY":0,"sourceW":82,"sourceH":168},
"27":{"x":885,"y":959,"w":82,"h":168,"offX":0,"offY":0,"sourceW":82,"sourceH":168},
"28":{"x":1911,"y":917,"w":82,"h":168,"offX":0,"offY":0,"sourceW":82,"sourceH":168},
"29":{"x":1827,"y":917,"w":82,"h":168,"offX":0,"offY":0,"sourceW":82,"sourceH":168},
"30":{"x":373,"y":897,"w":82,"h":168,"offX":0,"offY":0,"sourceW":82,"sourceH":168},
"31":{"x":289,"y":897,"w":82,"h":168,"offX":0,"offY":0,"sourceW":82,"sourceH":168},
"32":{"x":457,"y":896,"w":82,"h":168,"offX":0,"offY":0,"sourceW":82,"sourceH":168},
"33":{"x":205,"y":878,"w":82,"h":168,"offX":0,"offY":0,"sourceW":82,"sourceH":168},
"34":{"x":1827,"y":771,"w":144,"h":144,"offX":0,"offY":0,"sourceW":144,"sourceH":144},
"35":{"x":1681,"y":671,"w":144,"h":144,"offX":0,"offY":0,"sourceW":144,"sourceH":144},
"36":{"x":609,"y":839,"w":144,"h":144,"offX":0,"offY":0,"sourceW":144,"sourceH":144},
"37":{"x":1681,"y":817,"w":144,"h":144,"offX":0,"offY":0,"sourceW":144,"sourceH":144},
"38":{"x":1,"y":725,"w":150,"h":151,"offX":0,"offY":0,"sourceW":150,"sourceH":151},
"39":{"x":1890,"y":154,"w":150,"h":151,"offX":0,"offY":0,"sourceW":150,"sourceH":151},
"40":{"x":457,"y":744,"w":150,"h":150,"offX":0,"offY":0,"sourceW":150,"sourceH":150},
"41":{"x":1890,"y":1,"w":150,"h":151,"offX":0,"offY":0,"sourceW":150,"sourceH":151},
"42":{"x":305,"y":744,"w":150,"h":151,"offX":0,"offY":0,"sourceW":150,"sourceH":151},
"43":{"x":153,"y":725,"w":150,"h":151,"offX":0,"offY":0,"sourceW":150,"sourceH":151},
"44":{"x":1,"y":557,"w":166,"h":166,"offX":0,"offY":0,"sourceW":166,"sourceH":166},
"45":{"x":1831,"y":435,"w":166,"h":166,"offX":0,"offY":0,"sourceW":166,"sourceH":166},
"46":{"x":1513,"y":671,"w":166,"h":166,"offX":0,"offY":0,"sourceW":166,"sourceH":166},
"47":{"x":1345,"y":671,"w":166,"h":166,"offX":0,"offY":0,"sourceW":166,"sourceH":166},
"48":{"x":1177,"y":671,"w":166,"h":166,"offX":0,"offY":0,"sourceW":166,"sourceH":166},
"49":{"x":1009,"y":671,"w":166,"h":166,"offX":0,"offY":0,"sourceW":166,"sourceH":166},
"50":{"x":841,"y":671,"w":166,"h":166,"offX":0,"offY":0,"sourceW":166,"sourceH":166},
"51":{"x":673,"y":671,"w":166,"h":166,"offX":0,"offY":0,"sourceW":166,"sourceH":166},
"52":{"x":1831,"y":603,"w":166,"h":166,"offX":0,"offY":0,"sourceW":166,"sourceH":166},
"53":{"x":505,"y":576,"w":166,"h":166,"offX":0,"offY":0,"sourceW":166,"sourceH":166},
"54":{"x":337,"y":576,"w":166,"h":166,"offX":0,"offY":0,"sourceW":166,"sourceH":166},
"55":{"x":169,"y":557,"w":166,"h":166,"offX":0,"offY":0,"sourceW":166,"sourceH":166},
"56":{"x":423,"y":222,"w":206,"h":206,"offX":0,"offY":0,"sourceW":206,"sourceH":206},
"57":{"x":1679,"y":218,"w":209,"h":215,"offX":0,"offY":0,"sourceW":209,"sourceH":215},
"58":{"x":1,"y":1,"w":207,"h":219,"offX":0,"offY":0,"sourceW":207,"sourceH":219}}}